square_datastore_client/__init__.py
square_datastore_client/datastore_client.py
square_datastore_client-0.0.3.dist-info/METADATA
square_datastore_client-0.0.3.dist-info/WHEEL
square_datastore_client-0.0.3.dist-info/top_level.txt
square_datastore_client-0.0.3.dist-info/RECORD
