Metadata-Version: 2.1
Name: square-datastore-client
Version: 0.0.3
Summary: UNKNOWN
Home-page: https://github.com/UKP-SQuARE/square-datastore-client
Author: UKP
Author-email: baumgaertner@ukp.informatik.tu-darmstadt.de
License: MIT
Download-URL: https://github.com/UKP-SQuARE/square-datastore-client/archive/refs/tags/v0.0.3.tar.gz
Platform: UNKNOWN
Requires-Dist: requests (>=2.28.1)
Requires-Dist: square-auth (>=0.0.14)
